COPYING
MANIFEST.in
README.md
setup.py
surface_dynamics/__init__.py
surface_dynamics/all.py
surface_dynamics/version.py
surface_dynamics.egg-info/PKG-INFO
surface_dynamics.egg-info/SOURCES.txt
surface_dynamics.egg-info/dependency_links.txt
surface_dynamics.egg-info/top_level.txt
surface_dynamics/databases/__init__.py
surface_dynamics/databases/flat_surfaces.py
surface_dynamics/databases/cylinder_diagrams/cyl_diags-1_1_1_1-c-1
surface_dynamics/databases/cylinder_diagrams/cyl_diags-1_1_1_1-c-2
surface_dynamics/databases/cylinder_diagrams/cyl_diags-1_1_1_1-c-3
surface_dynamics/databases/cylinder_diagrams/cyl_diags-1_1_1_1-c-4
surface_dynamics/databases/cylinder_diagrams/cyl_diags-1_1_1_1-c-5
surface_dynamics/databases/cylinder_diagrams/cyl_diags-1_1_1_1-c-6
surface_dynamics/databases/cylinder_diagrams/cyl_diags-2_1_1-c-1
surface_dynamics/databases/cylinder_diagrams/cyl_diags-2_1_1-c-2
surface_dynamics/databases/cylinder_diagrams/cyl_diags-2_1_1-c-3
surface_dynamics/databases/cylinder_diagrams/cyl_diags-2_1_1-c-4
surface_dynamics/databases/cylinder_diagrams/cyl_diags-2_1_1-c-5
surface_dynamics/databases/cylinder_diagrams/cyl_diags-2_1_1_1_1-c-1
surface_dynamics/databases/cylinder_diagrams/cyl_diags-2_1_1_1_1-c-2
surface_dynamics/databases/cylinder_diagrams/cyl_diags-2_1_1_1_1-c-3
surface_dynamics/databases/cylinder_diagrams/cyl_diags-2_1_1_1_1-c-4
surface_dynamics/databases/cylinder_diagrams/cyl_diags-2_1_1_1_1-c-5
surface_dynamics/databases/cylinder_diagrams/cyl_diags-2_1_1_1_1-c-6
surface_dynamics/databases/cylinder_diagrams/cyl_diags-2_1_1_1_1-c-7
surface_dynamics/databases/cylinder_diagrams/cyl_diags-2_1_1_1_1-c-8
surface_dynamics/databases/cylinder_diagrams/cyl_diags-2_2-odd-1
surface_dynamics/databases/cylinder_diagrams/cyl_diags-2_2-odd-2
surface_dynamics/databases/cylinder_diagrams/cyl_diags-2_2-odd-3
surface_dynamics/databases/cylinder_diagrams/cyl_diags-2_2-odd-4
surface_dynamics/databases/cylinder_diagrams/cyl_diags-2_2_1_1-c-1
surface_dynamics/databases/cylinder_diagrams/cyl_diags-2_2_1_1-c-2
surface_dynamics/databases/cylinder_diagrams/cyl_diags-2_2_1_1-c-3
