Metadata-Version: 2.1
Name: surface-dynamics
Version: 0.6.0
Summary: Dynamics on surfaces
Author: Vincent Delecroix
Author-email: vincent.delecroix@u-bordeaux.fr
License: GPL v2
Project-URL: Bug Tracker, https://github.com/flatsurf/surface-dynamics/issues
Project-URL: Documentation, https://flatsurf.github.io/surface-dynamics/
Project-URL: Source Code, https://github.com/flatsurf/surface-dynamics
Keywords: surfaces,dynamics,geometry,flat surfaces,Abelian differentials,quadratic differentials,Riemann surfaces
Classifier: Development Status :: 4 - Beta
Classifier: Intended Audience :: Science/Research
Classifier: License :: OSI Approved :: GNU General Public License v2 or later (GPLv2+)
Classifier: Operating System :: OS Independent
Classifier: Programming Language :: C
Classifier: Programming Language :: C++
Classifier: Programming Language :: Python
Classifier: Programming Language :: Cython
Classifier: Topic :: Scientific/Engineering :: Mathematics
License-File: COPYING
